contspy/__about__.py
contspy/__init__.py
contspy/cli.py
contspy/main.py
contspy/outputs.py
contspy/plotting.py
contspy/solvers.py
contspy/spectral.py
contspy-0.0.4.dist-info/LICENSE
contspy-0.0.4.dist-info/METADATA
contspy-0.0.4.dist-info/WHEEL
contspy-0.0.4.dist-info/entry_points.txt
contspy-0.0.4.dist-info/top_level.txt
contspy-0.0.4.dist-info/RECORD
