Metadata-Version: 2.1
Name: contspy
Version: 0.0.4
Summary: Numerical continuation tools for partial differential equations using spectral elements method
Home-page: https://github.com/ajacquey/contspy
Author: Antoine B. Jacquey
Author-email: ajacquey@mit.edu
License: MIT
Project-URL: Code, https://github.com/ajacquey/contspy
Project-URL: Issues, https://github.com/ajacquey/contspy/issues
Platform: any
Classifier: Development Status :: 3 - Alpha
Classifier: Intended Audience :: Science/Research
Classifier: License :: OSI Approved :: MIT License
Classifier: Operating System :: OS Independent
Classifier: Programming Language :: Python
Classifier: Programming Language :: Python :: 3
Classifier: Programming Language :: Python :: 3.5
Classifier: Programming Language :: Python :: 3.6
Classifier: Programming Language :: Python :: 3.7
Classifier: Programming Language :: Python :: 3.8
Classifier: Topic :: Scientific/Engineering
Classifier: Topic :: Scientific/Engineering :: Mathematics
Classifier: Topic :: Scientific/Engineering :: Physics
Requires-Python: >=3.5
Requires-Dist: numpy
Requires-Dist: termcolor
Requires-Dist: matplotlib
Requires-Dist: importlib-metadata ; python_version < "3.8"
